odoo/addons/account_invoice_refund_reason_skip_anglo_saxon/README.rst
odoo/addons/account_invoice_refund_reason_skip_anglo_saxon/__init__.py
odoo/addons/account_invoice_refund_reason_skip_anglo_saxon/__manifest__.py
odoo/addons/account_invoice_refund_reason_skip_anglo_saxon/i18n/account_invoice_refund_reason_skip_anglo_saxon.pot
odoo/addons/account_invoice_refund_reason_skip_anglo_saxon/i18n/es.po
odoo/addons/account_invoice_refund_reason_skip_anglo_saxon/i18n/it.po
odoo/addons/account_invoice_refund_reason_skip_anglo_saxon/models/__init__.py
odoo/addons/account_invoice_refund_reason_skip_anglo_saxon/models/account_invoice_refund_reason.py
odoo/addons/account_invoice_refund_reason_skip_anglo_saxon/models/account_move.py
odoo/addons/account_invoice_refund_reason_skip_anglo_saxon/readme/CONFIGURE.rst
odoo/addons/account_invoice_refund_reason_skip_anglo_saxon/readme/CONTRIBUTORS.rst
odoo/addons/account_invoice_refund_reason_skip_anglo_saxon/readme/DESCRIPTION.rst
odoo/addons/account_invoice_refund_reason_skip_anglo_saxon/static/description/icon.png
odoo/addons/account_invoice_refund_reason_skip_anglo_saxon/static/description/index.html
odoo/addons/account_invoice_refund_reason_skip_anglo_saxon/tests/__init__.py
odoo/addons/account_invoice_refund_reason_skip_anglo_saxon/tests/test_account_invoice_refund_reason_skip_anglo_saxon.py
odoo/addons/account_invoice_refund_reason_skip_anglo_saxon/views/account_invoice_refund_reason_view.xml
odoo14_addon_account_invoice_refund_reason_skip_anglo_saxon-14.0.1.0.1.dev7.dist-info/METADATA
odoo14_addon_account_invoice_refund_reason_skip_anglo_saxon-14.0.1.0.1.dev7.dist-info/WHEEL
odoo14_addon_account_invoice_refund_reason_skip_anglo_saxon-14.0.1.0.1.dev7.dist-info/top_level.txt
odoo14_addon_account_invoice_refund_reason_skip_anglo_saxon-14.0.1.0.1.dev7.dist-info/RECORD
